.gitignore
LICENSE
README.md
requirements.txt
setup.cfg
setup.py
cadCAD_diagram/__init__.py
cadCAD_diagram/config_diagram.py
cadCAD_diagram.egg-info/PKG-INFO
cadCAD_diagram.egg-info/SOURCES.txt
cadCAD_diagram.egg-info/dependency_links.txt
cadCAD_diagram.egg-info/requires.txt
cadCAD_diagram.egg-info/top_level.txt
examples/sample_1.ipynb
examples/.ipynb_checkpoints/sample_1-checkpoint.ipynb
tests/__init__.py
tests/test_run.py