Metadata-Version: 1.0
Name: cadCAD-diagram
Version: 0.0.1.3
Summary: Diagram tool for cadCAD
Home-page: https://github.com/danlessa/cadCAD_diagram
Author: Danilo Lessa Bernardineli
Author-email: danilo@block.science, danilo.lessa@gmail.com
License: UNKNOWN
Platform: UNKNOWN
